FreeplanIr/__init__.py
FreeplanIr/main.py
FreeplanIr-1.0.5.dist-info/LICENSE.txt
FreeplanIr-1.0.5.dist-info/METADATA
FreeplanIr-1.0.5.dist-info/WHEEL
FreeplanIr-1.0.5.dist-info/top_level.txt
FreeplanIr-1.0.5.dist-info/RECORD
