Metadata-Version: 2.1
Name: FreeplanIr
Version: 1.0.5
Summary: 一个可以解析freeplan *.mm格式文件的工具
Home-page: https://github.com/leslie110
Author: wangdashuai
Author-email: hanchaodaming@outlook.com
Classifier: Programming Language :: Python :: 3
Classifier: License :: OSI Approved :: MIT License
Classifier: Operating System :: OS Independent
Requires-Python: >=3.6
License-File: LICENSE.txt
Requires-Dist: XlsxWriter (>=3.1.1)
